{
    "web": {
        "client_id": "918511553661-hj0glsd92crjkecnjacvvmf0d61fum3v.apps.googleusercontent.com",
        "project_id": "netflix-clone-334611",
        "auth_uri": "https://accounts.google.com/o/oauth2/auth",
        "token_uri": "https://oauth2.googleapis.com/token",
        "auth_provider_x509_cert_url": "https://www.googleapis.com/oauth2/v1/certs",
        "client_secret": "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",
        "redirect_uris": [
            "http://localhost:3000/api/auth/callback/google",
            "https://netflix-clone-weld-ten.vercel.app"
        ],
        "javascript_origins": [
            "http://localhost:3000",
            "https://netflix-clone-weld-ten.vercel.app"
        ]
    }
}